README.md
setup.py
port_pulumi/__init__.py
port_pulumi/_inputs.py
port_pulumi/_utilities.py
port_pulumi/action.py
port_pulumi/action_permissions.py
port_pulumi/aggregation_properties.py
port_pulumi/aggregation_property.py
port_pulumi/blueprint.py
port_pulumi/blueprint_permissions.py
port_pulumi/entity.py
port_pulumi/folder.py
port_pulumi/get_search.py
port_pulumi/integration.py
port_pulumi/organization_secret.py
port_pulumi/outputs.py
port_pulumi/page.py
port_pulumi/page_permissions.py
port_pulumi/provider.py
port_pulumi/pulumi-plugin.json
port_pulumi/py.typed
port_pulumi/scorecard.py
port_pulumi/system_blueprint.py
port_pulumi/team.py
port_pulumi/webhook.py
port_pulumi.egg-info/PKG-INFO
port_pulumi.egg-info/SOURCES.txt
port_pulumi.egg-info/dependency_links.txt
port_pulumi.egg-info/not-zip-safe
port_pulumi.egg-info/requires.txt
port_pulumi.egg-info/top_level.txt
port_pulumi/config/__init__.py
port_pulumi/config/__init__.pyi
port_pulumi/config/vars.py